jupyter_code_server/__init__.py
jupyter_code_server/icons/vscode.svg
jupyter_code_server-1.2.dist-info/licenses/LICENSE
jupyter_code_server-1.2.dist-info/METADATA
jupyter_code_server-1.2.dist-info/WHEEL
jupyter_code_server-1.2.dist-info/entry_points.txt
jupyter_code_server-1.2.dist-info/top_level.txt
jupyter_code_server-1.2.dist-info/RECORD
