Metadata-Version: 2.4
Name: jupyter_code_server
Version: 1.2
Summary: Running the Visual Studio Code Web IDE inside the Jupyter environment
Author-email: Marcel-Brian Wilkowsky <marcel.wilkowsky@uni-paderborn.de>
License: MIT License
Classifier: Programming Language :: Python :: 3.8
Requires-Python: >=3.8
License-File: LICENSE
Requires-Dist: jupyter-server-proxy>=4.1.2
Dynamic: license-file
